{"KXCS2GAME-26JUL100600AESTA-AE":{"can_close_early":true,"close_time":"2026-07-24T10:00:00Z","created_time":"2026-07-09T17:00:41.490501Z","custom_strike":{"esports_competitor":"cc2f5a8d-88e2-4844-8fbc-20b0e9984d6d"},"early_close_condition":"This market will close and expire after a winner is declared.","event_ticker":"KXCS2GAME-26JUL100600AESTA","expected_expiration_time":"2026-07-10T14:00:00Z","expiration_time":"2026-07-24T10:00:00Z","expiration_value":"","last_price_dollars":"0.5600","latest_expiration_time":"2026-07-24T10:00:00Z","liquidity_dollars":"0.0000","market_type":"binary","no_ask_dollars":"0.4800","no_bid_dollars":"0.4400","no_sub_title":"Alter Ego","notional_value_dollars":"1.0000","occurrence_datetime":"2026-07-10T14:00:00Z","open_interest_fp":"561.59","open_time":"2026-07-09T17:05:00Z","previous_price_dollars":"0.0000","previous_yes_ask_dollars":"0.0000","previous_yes_bid_dollars":"0.0000","price_level_structure":"linear_cent","price_ranges":[{"end":"1.0000","start":"0.0000","step":"0.0100"}],"result":"","rules_primary":"If Alter Ego wins the BLAST Open Asian Qualifier 2026: Alter Ego vs. 5star CS2 match originally scheduled for Jul 10, 2026 at 6:00 AM EDT, then the market resolves to Yes.","rules_secondary":"","settlement_timer_seconds":116,"status":"active","strike_type":"structured","ticker":"KXCS2GAME-26JUL100600AESTA-AE","title":"Will Alter Ego win the Alter Ego vs. 5star CS2 match?","updated_time":"2026-07-09T17:05:00.684065Z","volume_24h_fp":"611.39","volume_fp":"611.39","yes_ask_dollars":"0.5600","yes_ask_size_fp":"304.91","yes_bid_dollars":"0.5200","yes_bid_size_fp":"39.00","yes_sub_title":"Alter Ego"},"KXCS2GAME-26JUL100600AESTA-STA":{"can_close_early":true,"close_time":"2026-07-24T10:00:00Z","created_time":"2026-07-09T17:00:41.490501Z","custom_strike":{"esports_competitor":"7c17d5a5-2e69-47c2-97fc-763f36d7540c"},"early_close_condition":"This market will close and expire after a winner is declared.","event_ticker":"KXCS2GAME-26JUL100600AESTA","expected_expiration_time":"2026-07-10T14:00:00Z","expiration_time":"2026-07-24T10:00:00Z","expiration_value":"","last_price_dollars":"0.4800","latest_expiration_time":"2026-07-24T10:00:00Z","liquidity_dollars":"0.0000","market_type":"binary","no_ask_dollars":"0.5600","no_bid_dollars":"0.5200","no_sub_title":"5star","notional_value_dollars":"1.0000","occurrence_datetime":"2026-07-10T14:00:00Z","open_interest_fp":"748.93","open_time":"2026-07-09T17:05:00Z","previous_price_dollars":"0.0000","previous_yes_ask_dollars":"0.0000","previous_yes_bid_dollars":"0.0000","price_level_structure":"linear_cent","price_ranges":[{"end":"1.0000","start":"0.0000","step":"0.0100"}],"result":"","rules_primary":"If 5star wins the BLAST Open Asian Qualifier 2026: Alter Ego vs. 5star CS2 match originally scheduled for Jul 10, 2026 at 6:00 AM EDT, then the market resolves to Yes.","rules_secondary":"","settlement_timer_seconds":116,"status":"active","strike_type":"structured","ticker":"KXCS2GAME-26JUL100600AESTA-STA","title":"Will 5star win the Alter Ego vs. 5star CS2 match?","updated_time":"2026-07-09T17:05:00.684065Z","volume_24h_fp":"748.93","volume_fp":"748.93","yes_ask_dollars":"0.4800","yes_ask_size_fp":"199.90","yes_bid_dollars":"0.4400","yes_bid_size_fp":"69.00","yes_sub_title":"5star"}}