{"KXDOTA2GAME-26JUL110730LVLUPL1GA-L1GA":{"can_close_early":true,"close_time":"2026-07-25T11:30:00Z","created_time":"2026-07-09T16:50:33.592285Z","custom_strike":{"esports_competitor":"a6b47164-58f7-4f08-9c3c-296312d51d34"},"early_close_condition":"This market will close and expire after a winner is declared.","event_ticker":"KXDOTA2GAME-26JUL110730LVLUPL1GA","expected_expiration_time":"2026-07-11T15:30:00Z","expiration_time":"2026-07-25T11:30:00Z","expiration_value":"","last_price_dollars":"0.0000","latest_expiration_time":"2026-07-25T11:30:00Z","liquidity_dollars":"0.0000","market_type":"binary","no_ask_dollars":"0.8200","no_bid_dollars":"0.3000","no_sub_title":"L1ga Team","notional_value_dollars":"1.0000","occurrence_datetime":"2026-07-11T15:30:00Z","open_interest_fp":"0.00","open_time":"2026-07-09T16:55:00Z","previous_price_dollars":"0.0000","previous_yes_ask_dollars":"0.0000","previous_yes_bid_dollars":"0.0000","price_level_structure":"linear_cent","price_ranges":[{"end":"1.0000","start":"0.0000","step":"0.0100"}],"result":"","rules_primary":"If L1ga Team wins Esports World Cup 2026: Level UP vs. L1ga Team Dota 2 match originally scheduled for Jul 11, 2026 at 7:30 AM EDT, then the market resolves to Yes.","rules_secondary":"","settlement_timer_seconds":300,"status":"active","strike_type":"structured","ticker":"KXDOTA2GAME-26JUL110730LVLUPL1GA-L1GA","title":"Will L1ga Team win the Level UP vs. L1ga Team Dota 2 match?","updated_time":"2026-07-09T16:55:00.685639Z","volume_24h_fp":"0.00","volume_fp":"0.00","yes_ask_dollars":"0.7000","yes_ask_size_fp":"100.00","yes_bid_dollars":"0.1800","yes_bid_size_fp":"20.00","yes_sub_title":"L1ga Team"},"KXDOTA2GAME-26JUL110730LVLUPL1GA-LVLUP":{"can_close_early":true,"close_time":"2026-07-25T11:30:00Z","created_time":"2026-07-09T16:50:33.592285Z","custom_strike":{"esports_competitor":"dd6c4369-f22e-4a5c-9aed-79c39f55a5de"},"early_close_condition":"This market will close and expire after a winner is declared.","event_ticker":"KXDOTA2GAME-26JUL110730LVLUPL1GA","expected_expiration_time":"2026-07-11T15:30:00Z","expiration_time":"2026-07-25T11:30:00Z","expiration_value":"","last_price_dollars":"0.0000","latest_expiration_time":"2026-07-25T11:30:00Z","liquidity_dollars":"0.0000","market_type":"binary","no_ask_dollars":"0.8200","no_bid_dollars":"0.3000","no_sub_title":"Level UP","notional_value_dollars":"1.0000","occurrence_datetime":"2026-07-11T15:30:00Z","open_interest_fp":"0.00","open_time":"2026-07-09T16:55:00Z","previous_price_dollars":"0.0000","previous_yes_ask_dollars":"0.0000","previous_yes_bid_dollars":"0.0000","price_level_structure":"linear_cent","price_ranges":[{"end":"1.0000","start":"0.0000","step":"0.0100"}],"result":"","rules_primary":"If Level UP wins Esports World Cup 2026: Level UP vs. L1ga Team Dota 2 match originally scheduled for Jul 11, 2026 at 7:30 AM EDT, then the market resolves to Yes.","rules_secondary":"","settlement_timer_seconds":300,"status":"active","strike_type":"structured","ticker":"KXDOTA2GAME-26JUL110730LVLUPL1GA-LVLUP","title":"Will Level UP win the Level UP vs. L1ga Team Dota 2 match?","updated_time":"2026-07-09T16:55:00.685639Z","volume_24h_fp":"0.00","volume_fp":"0.00","yes_ask_dollars":"0.7000","yes_ask_size_fp":"100.00","yes_bid_dollars":"0.1800","yes_bid_size_fp":"20.00","yes_sub_title":"Level UP"},"KXDOTA2GAME-26JUL110730LVLUPL1GA-TIE":{"can_close_early":true,"close_time":"2026-07-25T11:30:00Z","created_time":"2026-07-09T16:50:33.592285Z","custom_strike":{"esports_competitor":"05f692cd-4d6e-4a74-ac78-15e426ffd954"},"early_close_condition":"This market will close and expire after a winner is declared.","event_ticker":"KXDOTA2GAME-26JUL110730LVLUPL1GA","expected_expiration_time":"2026-07-11T15:30:00Z","expiration_time":"2026-07-25T11:30:00Z","expiration_value":"","last_price_dollars":"0.0000","latest_expiration_time":"2026-07-25T11:30:00Z","liquidity_dollars":"0.0000","market_type":"binary","no_ask_dollars":"0.8200","no_bid_dollars":"0.3000","no_sub_title":"Tie","notional_value_dollars":"1.0000","occurrence_datetime":"2026-07-11T15:30:00Z","open_interest_fp":"0.00","open_time":"2026-07-09T16:55:00Z","previous_price_dollars":"0.0000","previous_yes_ask_dollars":"0.0000","previous_yes_bid_dollars":"0.0000","price_level_structure":"linear_cent","price_ranges":[{"end":"1.0000","start":"0.0000","step":"0.0100"}],"result":"","rules_primary":"If Tie wins Esports World Cup 2026: Level UP vs. L1ga Team Dota 2 match originally scheduled for Jul 11, 2026 at 7:30 AM EDT, then the market resolves to Yes.","rules_secondary":"","settlement_timer_seconds":300,"status":"active","strike_type":"structured","ticker":"KXDOTA2GAME-26JUL110730LVLUPL1GA-TIE","title":"Will Tie win the Level UP vs. L1ga Team Dota 2 match?","updated_time":"2026-07-09T16:55:00.685639Z","volume_24h_fp":"0.00","volume_fp":"0.00","yes_ask_dollars":"0.7000","yes_ask_size_fp":"100.00","yes_bid_dollars":"0.1800","yes_bid_size_fp":"20.00","yes_sub_title":"Tie"}}